file_util/__init__.py
file_util/file_util.py
file_util-0.1.6.dist-info/WHEEL
file_util-0.1.6.dist-info/METADATA
file_util-0.1.6.dist-info/RECORD
